totvserprm/__init__.py
totvserprm/auth.py
totvserprm/baseapi.py
totvserprm/educational.py
totvserprm/exceptions.py
totvserprm/financial.py
totvserprm/retrieve.py
totvserprm/utils.py
totvserprm-1.11.2.dist-info/DESCRIPTION.rst
totvserprm-1.11.2.dist-info/METADATA
totvserprm-1.11.2.dist-info/RECORD
totvserprm-1.11.2.dist-info/WHEEL
totvserprm-1.11.2.dist-info/metadata.json
totvserprm-1.11.2.dist-info/top_level.txt
