Metadata-Version: 2.0
Name: totvserprm
Version: 1.11.2
Summary: API para webservices do TOTVS ERP RM
Home-page: https://github.com/grupoandrademartins/totvserprm
Author: Rafael G. Winter, Túlio Cesar Martins
Author-email: totvs-erp-rm-python@googlegroups.com
License: MIT
Keywords: totvs webservice erp rm soap api
Platform: UNKNOWN
Requires-Dist: dicttoxml
Requires-Dist: lxml
Requires-Dist: requests
Requires-Dist: zeep
